norilog/__init__.py
norilog/static/style.css
norilog/templates/index.html
norilog-0.9.0.dist-info/METADATA
norilog-0.9.0.dist-info/RECORD
norilog-0.9.0.dist-info/WHEEL
norilog-0.9.0.dist-info/entry_points.txt
norilog-0.9.0.dist-info/top_level.txt
