Metadata-Version: 2.1
Name: norilog
Version: 0.9.0
Summary: The NoriLog web application.
Home-page: https://github.com/beproud/norilog/
Author: BeProud
Author-email: project@beproud.jp
License: BSD License
Keywords: web,norilog
Platform: UNKNOWN
Classifier: Development Status :: 4 - Beta
Classifier: Framework :: Flask
Classifier: License :: OSI Approved :: BSD License
Classifier: Programming Language :: Python
Classifier: Programming Language :: Python :: 3.6
Requires-Python: >=3.6
Requires-Dist: Flask
